online_triplet_loss/__init__.py
online_triplet_loss/_nbdev.py
online_triplet_loss/losses.py
online_triplet_loss-0.0.6.dist-info/LICENSE
online_triplet_loss-0.0.6.dist-info/METADATA
online_triplet_loss-0.0.6.dist-info/WHEEL
online_triplet_loss-0.0.6.dist-info/entry_points.txt
online_triplet_loss-0.0.6.dist-info/top_level.txt
online_triplet_loss-0.0.6.dist-info/RECORD
