Metadata-Version: 2.1
Name: online-triplet-loss
Version: 0.0.6
Summary: "Online mining triplet losses for Pytorch"
Home-page: https://github.com/NegatioN/OnlineMiningTripletLoss
Author: "Joakim Rishaug"
Author-email: "joakimrishaug@notmyrealemail.com"
License: Apache Software License 2.0
Keywords: pytorch loss online triplet mining
Platform: UNKNOWN
Classifier: Development Status :: 3 - Alpha
Classifier: Intended Audience :: Developers
Classifier: License :: OSI Approved :: Apache Software License
Classifier: Natural Language :: English
Classifier: Programming Language :: Python :: 3.6
Classifier: Programming Language :: Python :: 3.7
Classifier: Programming Language :: Python :: 3.8
Requires-Python: >=3.6
Requires-Dist: numpy (>=1.15.4)
Requires-Dist: torch (>=1.1.0)
